[
  {
    "title": "MIỄN PHÍ GIAO HÀNG",
    "paragraph": "Áp dụng Free ship cho tất cả đơn hàng từ 500 nghìn, giao ngay trong vòng 24h"
  },
  {
    "title": "ĐỔI TRẢ DỄ DÀNG",
    "paragraph": "Đổi ngay trong ngày nếu sản phẩm bị lỗi sản xuất, giao sai yêu cầu của quý khách"
  },
  {
    "title": "TƯ VẤN 24/7",
    "paragraph": "Gọi hotline: 1900 6750 để được hỗ trợ ngay, hỗ trợ tư vấn mọi vấn đề về thể thao"
  },
  {
    "title": "THANH TOÁN ĐA DẠNG",
    "paragraph": "Thanh toán khi nhận hàng COD, Chuyển Khoản, Napas, Visa, ATM, Trả góp "
  }
]
